blue_combine/__init__.py
blue_combine/blue.py
blue_combine/matrices.py
blue_combine-0.2.dist-info/LICENSE.txt
blue_combine-0.2.dist-info/METADATA
blue_combine-0.2.dist-info/RECORD
blue_combine-0.2.dist-info/WHEEL
blue_combine-0.2.dist-info/top_level.txt
