Metadata-Version: 2.1
Name: blue-combine
Version: 0.2
Summary: Python package for the Best Linear Unbiased Estimate (BLUE) method
Home-page: https://github.com/jolange/BLUE-py
Author: Johannes Lange
License: GPL-3.0
Platform: UNKNOWN
Requires-Python: >=3
Requires-Dist: numpy
